{
  "cb4e58acdeea1cfb42b89a42126fbcc4" : {
    "statistic" : {
      "failed" : 0,
      "broken" : 0,
      "skipped" : 0,
      "passed" : 1,
      "unknown" : 0,
      "total" : 1
    },
    "items" : [ {
      "uid" : "c27c1f6d98d5b63f",
      "reportUrl" : "https://jagagi.github.io/cicd-py-example/3//#testresult/c27c1f6d98d5b63f",
      "status" : "passed",
      "time" : {
        "start" : 1623601768407,
        "stop" : 1623601768407,
        "duration" : 0
      }
    } ]
  },
  "8b7d100b89a9b0e22a8d6732c7ee0ba9" : {
    "statistic" : {
      "failed" : 0,
      "broken" : 0,
      "skipped" : 0,
      "passed" : 1,
      "unknown" : 0,
      "total" : 1
    },
    "items" : [ {
      "uid" : "b5a608c19fc3611a",
      "reportUrl" : "https://jagagi.github.io/cicd-py-example/3//#testresult/b5a608c19fc3611a",
      "status" : "passed",
      "time" : {
        "start" : 1623601768404,
        "stop" : 1623601768404,
        "duration" : 0
      }
    } ]
  },
  "dcb8fa11fdff83e2daf0e792014a33fe" : {
    "statistic" : {
      "failed" : 0,
      "broken" : 0,
      "skipped" : 0,
      "passed" : 1,
      "unknown" : 0,
      "total" : 1
    },
    "items" : [ {
      "uid" : "223df874f21ce4cd",
      "reportUrl" : "https://jagagi.github.io/cicd-py-example/3//#testresult/223df874f21ce4cd",
      "status" : "passed",
      "time" : {
        "start" : 1623601768406,
        "stop" : 1623601768406,
        "duration" : 0
      }
    } ]
  },
  "dce78d7dd5962c01ca0a9a6e9bc9920e" : {
    "statistic" : {
      "failed" : 0,
      "broken" : 0,
      "skipped" : 0,
      "passed" : 1,
      "unknown" : 0,
      "total" : 1
    },
    "items" : [ {
      "uid" : "3acc4470f7a58b7c",
      "reportUrl" : "https://jagagi.github.io/cicd-py-example/3//#testresult/3acc4470f7a58b7c",
      "status" : "passed",
      "time" : {
        "start" : 1623601768394,
        "stop" : 1623601768394,
        "duration" : 0
      }
    } ]
  }
}